<?xml version="1.0" encoding="utf-8"?>

<Deployment xmlns="http://schemas.microsoft.com/windowsphone/2012/deployment" AppPlatformVersion="8.0">
  <DefaultLanguage xmlns="" code="en-US"/>
  <App xmlns="" ProductID="{fb103e1e-df9b-4ea9-9c10-1e1bc9ddbf80}" Title="TelerikListViewXF.WinPhone" RuntimeType="Silverlight" Version="1.0.0.0" Genre="apps.normal"  Author="TelerikListViewXF.WinPhone author" Description="Sample description" Publisher="TelerikListViewXF.WinPhone" PublisherID="{e74ead0c-7b75-4031-b5fc-30f6046b3130}">
    <IconPath IsRelative="true" IsResource="false">Assets\ApplicationIcon.png</IconPath>
    <Capabilities>
      <Capability Name="ID_CAP_NETWORKING"/>
      <Capability Name="ID_CAP_MEDIALIB_AUDIO"/>
      <Capability Name="ID_CAP_MEDIALIB_PLAYBACK"/>
      <Capability Name="ID_CAP_SENSORS"/>
      <Capability Name="ID_CAP_WEBBROWSERCOMPONENT"/>
    </Capabilities>
    <Tasks>
      <DefaultTask  Name ="_default" NavigationPage="MainPage.xaml"/>
    </Tasks>
    <Tokens>
      <PrimaryToken TokenID="PhoneApp1Token" TaskName="_default">
        <TemplateFlip>
          <SmallImageURI IsRelative="true" IsResource="false">Assets\Tiles\FlipCycleTileSmall.png</SmallImageURI>
          <Count>0</Count>
          <BackgroundImageURI IsRelative="true" IsResource="false">Assets\Tiles\FlipCycleTileMedium.png</BackgroundImageURI>
          <Title>TelerikListViewXF.WinPhone</Title>
          <BackContent></BackContent>
          <BackBackgroundImageURI></BackBackgroundImageURI>
          <BackTitle></BackTitle>
          <DeviceLockImageURI></DeviceLockImageURI>
          <HasLarge></HasLarge>
        </TemplateFlip>
      </PrimaryToken>
    </Tokens>
    <ScreenResolutions>
      <ScreenResolution Name="ID_RESOLUTION_WVGA"/>
      <ScreenResolution Name="ID_RESOLUTION_WXGA"/>
      <ScreenResolution Name="ID_RESOLUTION_HD720P"/>
    </ScreenResolutions>
  </App>
</Deployment>
